__init__.py
barramento_de_mensagens/__init__.py
barramento_de_mensagens/bootstrap.py
barramento_de_mensagens/dominio.py
barramento_de_mensagens/manipuladores.py
barramento_de_mensagens/unidade_de_trabalho.py
barramento_de_mensagens/aplicacoes/__init__.py
barramento_de_mensagens/aplicacoes/banco_de_dados.py
barramento_de_mensagens/aplicacoes/celery.py
barramento_de_mensagens/aplicacoes/tarefas.py
barramento_de_mensagens/base/__init__.py
barramento_de_mensagens/base/barramento.py
barramento_de_mensagens/base/bootstrap.py
barramento_de_mensagens/base/entidades.py
barramento_de_mensagens/base/unidade_de_trabalho.py
barramento_de_mensagens-0.1.4.dist-info/METADATA
barramento_de_mensagens-0.1.4.dist-info/WHEEL
barramento_de_mensagens-0.1.4.dist-info/top_level.txt
barramento_de_mensagens-0.1.4.dist-info/RECORD
