Metadata-Version: 2.4
Name: barramento-de-mensagens
Version: 0.1.4
Summary: Biblioteca para barramento de mensagens
Requires-Python: >=3.11
Requires-Dist: build>=1.3.0
Requires-Dist: celery>=5.5.3
Requires-Dist: dotenv>=0.9.9
Requires-Dist: mypy>=1.17.1
Requires-Dist: pre-commit>=4.3.0
Requires-Dist: pytest>=8.4.1
Requires-Dist: ruff>=0.12.8
Requires-Dist: sentry-sdk>=2.34.1
Requires-Dist: sqlalchemy>=2.0.43
Requires-Dist: twine>=6.1.0
